asphalt/serialization/__init__.py
asphalt/serialization/api.py
asphalt/serialization/component.py
asphalt/serialization/marshalling.py
asphalt/serialization/object_codec.py
asphalt/serialization/py.typed
asphalt/serialization/serializers/__init__.py
asphalt/serialization/serializers/cbor.py
asphalt/serialization/serializers/json.py
asphalt/serialization/serializers/msgpack.py
asphalt/serialization/serializers/pickle.py
asphalt/serialization/serializers/yaml.py
asphalt_serialization-6.0.0.dist-info/LICENSE
asphalt_serialization-6.0.0.dist-info/METADATA
asphalt_serialization-6.0.0.dist-info/WHEEL
asphalt_serialization-6.0.0.dist-info/entry_points.txt
asphalt_serialization-6.0.0.dist-info/top_level.txt
asphalt_serialization-6.0.0.dist-info/RECORD
