Metadata-Version: 2.1
Name: asphalt-serialization
Version: 6.0.0
Summary: Serialization component for the Asphalt framework
Author-email: Alex Grönholm <alex.gronholm@nextday.fi>
License: Apache License 2.0
Project-URL: Homepage, https://github.com/asphalt-framework/asphalt-serialization
Classifier: Development Status :: 5 - Production/Stable
Classifier: Intended Audience :: Developers
Classifier: License :: OSI Approved :: Apache Software License
Classifier: Programming Language :: Python
Classifier: Programming Language :: Python :: 3
Classifier: Programming Language :: Python :: 3.7
Classifier: Programming Language :: Python :: 3.8
Classifier: Programming Language :: Python :: 3.9
Classifier: Programming Language :: Python :: 3.10
Classifier: Programming Language :: Python :: 3.11
Requires-Python: >=3.7
License-File: LICENSE
Requires-Dist: asphalt (~=4.8)
Requires-Dist: cbor2 (~=5.0) ; extra == "cbor" or extra == "test" or extra == "doc"
Requires-Dist: msgpack (~=1.0) ; extra == "msgpack" or extra == "test" or extra == "doc"
Requires-Dist: ruamel.yaml (>=0.15) ; extra == "yaml" or extra == "test" or extra == "doc"
Provides-Extra: cbor
Provides-Extra: doc
Requires-Dist: Sphinx (>=1.5) ; extra == 'doc'
Requires-Dist: sphinx-rtd-theme ; extra == 'doc'
Requires-Dist: sphinx-autodoc-typehints (>=1.0.5) ; extra == 'doc'
Requires-Dist: sphinxcontrib-asyncio (>=0.2.0) ; extra == 'doc'
Provides-Extra: msgpack
Provides-Extra: test
Requires-Dist: pytest ; extra == 'test'
Requires-Dist: pytest-cov ; extra == 'test'
Requires-Dist: pytest-asyncio ; extra == 'test'
Provides-Extra: yaml
